feature_selections/__init__.py
feature_selections/feature_selection.py
feature_selections/filters/__init__.py
feature_selections/filters/filter.py
feature_selections/heuristics/__init__.py
feature_selections/heuristics/heuristic.py
feature_selections/heuristics/other/__init__.py
feature_selections/heuristics/other/rand.py
feature_selections/heuristics/population_based/__init__.py
feature_selections/heuristics/population_based/differential.py
feature_selections/heuristics/population_based/genetic.py
feature_selections/heuristics/population_based/mbde.py
feature_selections/heuristics/population_based/pbil.py
feature_selections/heuristics/population_based/tide.py
feature_selections/heuristics/single_solution/__init__.py
feature_selections/heuristics/single_solution/backward.py
feature_selections/heuristics/single_solution/forward.py
feature_selections/heuristics/single_solution/local.py
feature_selections/heuristics/single_solution/simulated.py
feature_selections/heuristics/single_solution/tabu.py
tide_feature_selection-1.2.1.dist-info/licenses/LICENSE
utility/__init__.py
utility/utility.py
tide_feature_selection-1.2.1.dist-info/METADATA
tide_feature_selection-1.2.1.dist-info/WHEEL
tide_feature_selection-1.2.1.dist-info/top_level.txt
tide_feature_selection-1.2.1.dist-info/RECORD
