Metadata-Version: 2.4
Name: tide-feature-selection
Version: 1.2.1
Summary: Implements multiple type of filter methods and heuristics for the feature selection problem in machine learning as well as a new one: tournament in differential evolution
Home-page: https://github.com/thibaultanani/TiDE
Author: Thibault Anani, François Delbot, Jean-François Pradat-Peyre
Author-email: thibault.anani@gmail.com, francois.delbot@lip6.fr, jean-francois.pradat-peyre@lip6.fr
Maintainer: Thibault Anani
Maintainer-email: thibault.anani@gmail.com
Classifier: Programming Language :: Python :: 3
Classifier: License :: OSI Approved :: BSD License
Classifier: Operating System :: OS Independent
Requires-Python: >=3.7
License-File: LICENSE
Requires-Dist: numpy
Requires-Dist: openpyxl
Requires-Dist: pandas
Requires-Dist: psutil
Requires-Dist: scikit-learn
Requires-Dist: scipy
Dynamic: author
Dynamic: author-email
Dynamic: classifier
Dynamic: description
Dynamic: description-content-type
Dynamic: home-page
Dynamic: license-file
Dynamic: maintainer
Dynamic: maintainer-email
Dynamic: requires-dist
Dynamic: requires-python
Dynamic: summary
